shipaw/__init__.py
shipaw/config.py
shipaw/fapi/__init__.py
shipaw/fapi/alerts.py
shipaw/fapi/app.py
shipaw/fapi/backend.py
shipaw/fapi/callbacks.py
shipaw/fapi/emailer.py
shipaw/fapi/form_data.py
shipaw/fapi/requests.py
shipaw/fapi/responses.py
shipaw/fapi/routes_api.py
shipaw/fapi/routes_html.py
shipaw/fapi/shipment_booking.py
shipaw/fapi/ui_funcs.py
shipaw/logging.py
shipaw/logging_sql.py
shipaw/models/__init__.py
shipaw/models/address.py
shipaw/models/base.py
shipaw/models/label_file.py
shipaw/models/ship_types.py
shipaw/models/shipment.py
shipaw/models/str_enum_funcs.py
shipaw/one_shots.py
shipaw/providers/__init__.py
shipaw/providers/apc/__init__.py
shipaw/providers/apc/apc_funcs.py
shipaw/providers/apc/apc_provider.py
shipaw/providers/apc/response.py
shipaw/providers/apc/track.py
shipaw/providers/parcelforce/__init__.py
shipaw/providers/parcelforce/parcelforce_funcs.py
shipaw/providers/parcelforce/parcelforce_provider.py
shipaw/providers/provider_abc.py
shipaw/providers/registry.py
shipaw/providers/royal_mail/__init__.py
shipaw/providers/royal_mail/royal_mail_funcs.py
shipaw/providers/royal_mail/royal_mail_provider.py
shipaw/sql_helpers.py
shipaw/ui/static/favicon.svg
shipaw/ui/static/ship.css
shipaw/ui/static/ship.js
shipaw/ui/static/style.css
shipaw/ui/templates/alerts.html
shipaw/ui/templates/app_alerts.html
shipaw/ui/templates/base.html
shipaw/ui/templates/email_snips/email_base.html
shipaw/ui/templates/email_snips/label_email.html
shipaw/ui/templates/order_results.html
shipaw/ui/templates/order_summary.html
shipaw/ui/templates/shipping_form.html
shipaw/ui/templates/shipping_form_container.html
shipaw-0.3.27.dist-info/WHEEL
shipaw-0.3.27.dist-info/METADATA
shipaw-0.3.27.dist-info/RECORD
