Metadata-Version: 2.4
Name: shipaw
Version: 0.3.27
Summary: Shipping client
Author: pawrequest
Author-email: pawrequest <shipaw+pawrequest@users.noreply.github.com>
License-Expression: MIT
Requires-Dist: apc-hypaship==0.1.10
Requires-Dist: parcelforce-expresslink==0.1.12
Requires-Dist: royal-mail-click-and-drop==0.0.10
Requires-Dist: pawdf>=0.1.0
Requires-Dist: httpx>=0.28.1
Requires-Dist: pygments>=2.19.2
Requires-Dist: pydantic[email]>=2.11.9
Requires-Dist: pytest>=8.4.2
Requires-Dist: fastapi[standard]>=0.117.1
Requires-Dist: jinja2>=3.1.6
Requires-Dist: hatchling>=1.27.0
Requires-Dist: combadge[zeep]>=4.8.2
Requires-Dist: loguru>=0.7.3
Requires-Dist: thefuzz>=0.22.1
Requires-Dist: pydantic-extra-types>=2.10.5
Requires-Dist: pydantic-settings>=2.11.0
Requires-Dist: phonenumbers>=9.0.15
Requires-Dist: pywin32>=311
Requires-Dist: uvicorn>=0.37.0
Requires-Python: >=3.13
Project-URL: Homepage, https://github.com/pawrequest/shipaw
